Metadata-Version: 2.1
Name: sebastiancalculator
Version: 0.0.1
Summary: A very basic calculator
Home-page: UNKNOWN
Author: Sebastian harris
Author-email: sebastian.harris4@aphs.nsw.edu.au
License: MIT
Keywords: calculator
Platform: UNKNOWN
Classifier: Development Status :: 5 - Production/Stable
Classifier: Intended Audience :: Education
Classifier: Operating System :: Microsoft :: Windows :: Windows 10
Classifier: License :: OSI Approved :: MIT License
Classifier: Programming Language :: Python :: 3
License-File: LICENCE.txt
